find_episodes/__init__.py
find_episodes/cli.py
find_episodes/config.py
find_episodes/episodes.py
find_episodes-0.9.2.dist-info/AUTHORS.rst
find_episodes-0.9.2.dist-info/LICENSE.txt
find_episodes-0.9.2.dist-info/METADATA
find_episodes-0.9.2.dist-info/WHEEL
find_episodes-0.9.2.dist-info/entry_points.txt
find_episodes-0.9.2.dist-info/top_level.txt
find_episodes-0.9.2.dist-info/RECORD
